GeneratorPromptKit/__init__.py
GeneratorPromptKit/base.py
GeneratorPromptKit/function_templates.py
GeneratorPromptKit/llm_integration.py
GeneratorPromptKit/prompts.py
GeneratorPromptKit/support.py
GeneratorPromptKit/utils.py
generator_prompt_kit-1.0.3.dist-info/LICENSE
generator_prompt_kit-1.0.3.dist-info/METADATA
generator_prompt_kit-1.0.3.dist-info/WHEEL
generator_prompt_kit-1.0.3.dist-info/top_level.txt
generator_prompt_kit-1.0.3.dist-info/RECORD
