Metadata-Version: 2.1
Name: generator-prompt-kit
Version: 1.0.3
Summary: A Python Library for Automated Generator Prompting and Dataset Generation
Home-page: http://github.com/AmanPriyanshu/GeneratorPromptKit
Author: Aman Priyanshu and Supriti Vijay
Author-email: amanpriyanshusms2001@gmail.com
License: MIT
Keywords: llm llms llm-training dataset-generation automated-prompt-engineering prompt-engineering diverse-data data-science data dataset synthetic-dataset-generation synthetic-data augmentation data-augmentation
Classifier: Development Status :: 3 - Alpha
Classifier: Intended Audience :: Developers
Classifier: License :: OSI Approved :: MIT License
Classifier: Programming Language :: Python :: 3
License-File: LICENSE
Requires-Dist: numpy ==2.0.0
Requires-Dist: openai ==1.34.0
Requires-Dist: pandas ==2.2.2
Requires-Dist: tqdm ==4.66.4
